AUTHORS.txt
COPYING.txt
INSTALL.txt
MANIFEST.in
NEWS.txt
README.txt
TODO.txt
setup.py
pdfserenitynow/__init__.py
pdfserenitynow/pdfbursttops.py
pdfserenitynow/psconverttotif.py
pdfserenitynow/psn_utils.py
pdfserenitynow/serenifypdf.py
pdfserenitynow.egg-info/PKG-INFO
pdfserenitynow.egg-info/SOURCES.txt
pdfserenitynow.egg-info/dependency_links.txt
pdfserenitynow.egg-info/entry_points.txt
pdfserenitynow.egg-info/not-zip-safe
pdfserenitynow.egg-info/top_level.txt