Metadata-Version: 1.1
Name: pdfserenitynow
Version: 0.6.7
Summary: Create TIFs and JPGs from crappy PDFs
Home-page: https://sourceforge.net/p/pdfserenitynow/
Author: Ben Rousch
Author-email: brousch@gmail.com
License: MIT
Keywords: pdf print converter tiff jpg
Platform: UNKNOWN
Classifier: Development Status :: 5 - Production/Stable
Classifier: Environment :: Console
Classifier: Intended Audience :: System Administrators
Classifier: License :: OSI Approved :: GNU General Public License (GPL)
Classifier: Natural Language :: English
Classifier: Operating System :: MacOS :: MacOS X
Classifier: Operating System :: POSIX :: Linux
Classifier: Programming Language :: Python :: 3.3
Classifier: Programming Language :: Python :: 3.2
Classifier: Programming Language :: Python :: 3
Classifier: Topic :: Multimedia :: Graphics :: Graphics Conversion
Classifier: Topic :: Printing
Classifier: Topic :: Utilities
